README.md
setup.py
cargo_api/__init__.py
cargo_api/api.py
cargo_api/auth.py
cargo_api/auth_test.py
cargo_api.egg-info/PKG-INFO
cargo_api.egg-info/SOURCES.txt
cargo_api.egg-info/dependency_links.txt
cargo_api.egg-info/not-zip-safe
cargo_api.egg-info/requires.txt
cargo_api.egg-info/top_level.txt