Metadata-Version: 1.0
Name: cargo-api
Version: 0.3.0
Summary: API utility functions to handle API responses
Home-page: https://gitlab.cargo.one/python/cargo-api
Author: Mike Roetgers
Author-email: mr@cargo.one
License: MIT
Platform: UNKNOWN
